[
  {
    "category": "Program Committee Co-Chairs",
    "people": [
      {
        "name": "Vittorio Loretto",
        "affiliation": "Sapienza University of Rome",
        "pic": "http://socialdynamics.it/vittorioloreto/wp-content/uploads/2017/03/vittorio_satin_bn.png",
        "website": "http://socialdynamics.it/vittorioloreto/",
        "twitter": "https://twitter.com/loretoff"
      },
      {
        "name": "Kristina Lerman",
        "affiliation": "University of Southern California",
        "pic": "https://www.isi.edu/integration/people/lerman/img/KLerman.jpg",
        "website": "https://www.isi.edu/integration/people/lerman/",
        "twitter":"https://twitter.com/KristinaLerman"
      }
    ]
  },
  {
    "category": "Senior Area Chairs:",
    "people": [
      {
        "name": "TBA",
        "affiliation": "-",
        "pic": "",
        "website": "",
        "twitter": ""
      },
      {
        "name": "TBA",
        "affiliation": "-",
        "pic": "",
        "website": "",
        "twitter": ""
      },
      {
        "name": "TBA",
        "affiliation": "-",
        "pic": "",
        "website": "",
        "twitter": ""
      },
      {
        "name": "TBA",
        "affiliation": "-",
        "pic": "",
        "website": "",
        "twitter": ""
      },
      {
        "name": "TBA",
        "affiliation": "-",
        "pic": "",
        "website": "",
        "twitter": ""
      },
      {
        "name": "TBA",
        "affiliation": "-",
        "pic": "",
        "website": "",
        "twitter": ""
      }
    ]
  }
]
